{"validation_loss": 0.42471495270729065, "time_this_iter_s": 0.015469074249267578, "done": false, "timesteps_total": null, "episodes_total": null, "training_iteration": 1, "trial_id": "aa06d_00041", "experiment_id": "adfc3a5f2e334fc3a1a6a8cf9bcf68aa", "date": "2022-04-24_19-26-46", "timestamp": 1650821206, "time_total_s": 0.015469074249267578, "pid": 94957, "hostname": "marvin", "node_ip": "127.0.0.1", "config": {"layers": 3, "nodes": 38, "lr": 0.00026684710802752146, "optimizer_name": "adam", "number_of_minibatches": 1}, "time_since_restore": 0.015469074249267578, "timesteps_since_restore": 0, "iterations_since_restore": 1, "warmup_time": 0.003715991973876953}
{"validation_loss": 0.41180557012557983, "time_this_iter_s": 0.020061969757080078, "done": false, "timesteps_total": null, "episodes_total": null, "training_iteration": 2, "trial_id": "aa06d_00041", "experiment_id": "adfc3a5f2e334fc3a1a6a8cf9bcf68aa", "date": "2022-04-24_19-26-46", "timestamp": 1650821206, "time_total_s": 0.035531044006347656, "pid": 94957, "hostname": "marvin", "node_ip": "127.0.0.1", "config": {"layers": 3, "nodes": 38, "lr": 0.00026684710802752146, "optimizer_name": "adam", "number_of_minibatches": 1}, "time_since_restore": 0.035531044006347656, "timesteps_since_restore": 0, "iterations_since_restore": 2, "warmup_time": 0.003715991973876953}
{"validation_loss": 0.39964723587036133, "time_this_iter_s": 0.016581296920776367, "done": false, "timesteps_total": null, "episodes_total": null, "training_iteration": 3, "trial_id": "aa06d_00041", "experiment_id": "adfc3a5f2e334fc3a1a6a8cf9bcf68aa", "date": "2022-04-24_19-26-46", "timestamp": 1650821206, "time_total_s": 0.05211234092712402, "pid": 94957, "hostname": "marvin", "node_ip": "127.0.0.1", "config": {"layers": 3, "nodes": 38, "lr": 0.00026684710802752146, "optimizer_name": "adam", "number_of_minibatches": 1}, "time_since_restore": 0.05211234092712402, "timesteps_since_restore": 0, "iterations_since_restore": 3, "warmup_time": 0.003715991973876953}
{"validation_loss": 0.3882232904434204, "time_this_iter_s": 0.015486955642700195, "done": false, "timesteps_total": null, "episodes_total": null, "training_iteration": 4, "trial_id": "aa06d_00041", "experiment_id": "adfc3a5f2e334fc3a1a6a8cf9bcf68aa", "date": "2022-04-24_19-26-46", "timestamp": 1650821206, "time_total_s": 0.06759929656982422, "pid": 94957, "hostname": "marvin", "node_ip": "127.0.0.1", "config": {"layers": 3, "nodes": 38, "lr": 0.00026684710802752146, "optimizer_name": "adam", "number_of_minibatches": 1}, "time_since_restore": 0.06759929656982422, "timesteps_since_restore": 0, "iterations_since_restore": 4, "warmup_time": 0.003715991973876953}
{"validation_loss": 0.37752270698547363, "time_this_iter_s": 0.015857934951782227, "done": true, "timesteps_total": null, "episodes_total": null, "training_iteration": 5, "trial_id": "aa06d_00041", "experiment_id": "adfc3a5f2e334fc3a1a6a8cf9bcf68aa", "date": "2022-04-24_19-26-46", "timestamp": 1650821206, "time_total_s": 0.08345723152160645, "pid": 94957, "hostname": "marvin", "node_ip": "127.0.0.1", "config": {"layers": 3, "nodes": 38, "lr": 0.00026684710802752146, "optimizer_name": "adam", "number_of_minibatches": 1}, "time_since_restore": 0.08345723152160645, "timesteps_since_restore": 0, "iterations_since_restore": 5, "warmup_time": 0.003715991973876953}
