{"validation_loss": 13.17358112335205, "time_this_iter_s": 0.026585102081298828, "done": false, "timesteps_total": null, "episodes_total": null, "training_iteration": 1, "trial_id": "aef0c_00102", "experiment_id": "cea9589f16564c87ba569f9e55b73541", "date": "2022-04-24_20-10-09", "timestamp": 1650823809, "time_total_s": 0.026585102081298828, "pid": 95824, "hostname": "marvin", "node_ip": "127.0.0.1", "config": {"layers": 1, "nodes": 25, "activation_function": "ReLU()", "optimizer_name": "lbfgs", "lr": 0.00031708213771730994, "number_of_minibatches": 1}, "time_since_restore": 0.026585102081298828, "timesteps_since_restore": 0, "iterations_since_restore": 1, "warmup_time": 0.0017859935760498047}
{"validation_loss": 12.970255851745605, "time_this_iter_s": 0.05618619918823242, "done": false, "timesteps_total": null, "episodes_total": null, "training_iteration": 2, "trial_id": "aef0c_00102", "experiment_id": "cea9589f16564c87ba569f9e55b73541", "date": "2022-04-24_20-10-09", "timestamp": 1650823809, "time_total_s": 0.08277130126953125, "pid": 95824, "hostname": "marvin", "node_ip": "127.0.0.1", "config": {"layers": 1, "nodes": 25, "activation_function": "ReLU()", "optimizer_name": "lbfgs", "lr": 0.00031708213771730994, "number_of_minibatches": 1}, "time_since_restore": 0.08277130126953125, "timesteps_since_restore": 0, "iterations_since_restore": 2, "warmup_time": 0.0017859935760498047}
{"validation_loss": 11.439516067504883, "time_this_iter_s": 0.04156684875488281, "done": false, "timesteps_total": null, "episodes_total": null, "training_iteration": 3, "trial_id": "aef0c_00102", "experiment_id": "cea9589f16564c87ba569f9e55b73541", "date": "2022-04-24_20-10-09", "timestamp": 1650823809, "time_total_s": 0.12433815002441406, "pid": 95824, "hostname": "marvin", "node_ip": "127.0.0.1", "config": {"layers": 1, "nodes": 25, "activation_function": "ReLU()", "optimizer_name": "lbfgs", "lr": 0.00031708213771730994, "number_of_minibatches": 1}, "time_since_restore": 0.12433815002441406, "timesteps_since_restore": 0, "iterations_since_restore": 3, "warmup_time": 0.0017859935760498047}
{"validation_loss": 8.995542526245117, "time_this_iter_s": 0.04368185997009277, "done": false, "timesteps_total": null, "episodes_total": null, "training_iteration": 4, "trial_id": "aef0c_00102", "experiment_id": "cea9589f16564c87ba569f9e55b73541", "date": "2022-04-24_20-10-10", "timestamp": 1650823810, "time_total_s": 0.16802000999450684, "pid": 95824, "hostname": "marvin", "node_ip": "127.0.0.1", "config": {"layers": 1, "nodes": 25, "activation_function": "ReLU()", "optimizer_name": "lbfgs", "lr": 0.00031708213771730994, "number_of_minibatches": 1}, "time_since_restore": 0.16802000999450684, "timesteps_since_restore": 0, "iterations_since_restore": 4, "warmup_time": 0.0017859935760498047}
{"validation_loss": 7.77759313583374, "time_this_iter_s": 0.042179107666015625, "done": false, "timesteps_total": null, "episodes_total": null, "training_iteration": 5, "trial_id": "aef0c_00102", "experiment_id": "cea9589f16564c87ba569f9e55b73541", "date": "2022-04-24_20-10-10", "timestamp": 1650823810, "time_total_s": 0.21019911766052246, "pid": 95824, "hostname": "marvin", "node_ip": "127.0.0.1", "config": {"layers": 1, "nodes": 25, "activation_function": "ReLU()", "optimizer_name": "lbfgs", "lr": 0.00031708213771730994, "number_of_minibatches": 1}, "time_since_restore": 0.21019911766052246, "timesteps_since_restore": 0, "iterations_since_restore": 5, "warmup_time": 0.0017859935760498047}
{"validation_loss": 7.041770935058594, "time_this_iter_s": 0.042642831802368164, "done": false, "timesteps_total": null, "episodes_total": null, "training_iteration": 6, "trial_id": "aef0c_00102", "experiment_id": "cea9589f16564c87ba569f9e55b73541", "date": "2022-04-24_20-10-10", "timestamp": 1650823810, "time_total_s": 0.2528419494628906, "pid": 95824, "hostname": "marvin", "node_ip": "127.0.0.1", "config": {"layers": 1, "nodes": 25, "activation_function": "ReLU()", "optimizer_name": "lbfgs", "lr": 0.00031708213771730994, "number_of_minibatches": 1}, "time_since_restore": 0.2528419494628906, "timesteps_since_restore": 0, "iterations_since_restore": 6, "warmup_time": 0.0017859935760498047}
{"validation_loss": 6.5231499671936035, "time_this_iter_s": 0.04116415977478027, "done": false, "timesteps_total": null, "episodes_total": null, "training_iteration": 7, "trial_id": "aef0c_00102", "experiment_id": "cea9589f16564c87ba569f9e55b73541", "date": "2022-04-24_20-10-10", "timestamp": 1650823810, "time_total_s": 0.2940061092376709, "pid": 95824, "hostname": "marvin", "node_ip": "127.0.0.1", "config": {"layers": 1, "nodes": 25, "activation_function": "ReLU()", "optimizer_name": "lbfgs", "lr": 0.00031708213771730994, "number_of_minibatches": 1}, "time_since_restore": 0.2940061092376709, "timesteps_since_restore": 0, "iterations_since_restore": 7, "warmup_time": 0.0017859935760498047}
{"validation_loss": 6.076693534851074, "time_this_iter_s": 0.04292011260986328, "done": false, "timesteps_total": null, "episodes_total": null, "training_iteration": 8, "trial_id": "aef0c_00102", "experiment_id": "cea9589f16564c87ba569f9e55b73541", "date": "2022-04-24_20-10-10", "timestamp": 1650823810, "time_total_s": 0.3369262218475342, "pid": 95824, "hostname": "marvin", "node_ip": "127.0.0.1", "config": {"layers": 1, "nodes": 25, "activation_function": "ReLU()", "optimizer_name": "lbfgs", "lr": 0.00031708213771730994, "number_of_minibatches": 1}, "time_since_restore": 0.3369262218475342, "timesteps_since_restore": 0, "iterations_since_restore": 8, "warmup_time": 0.0017859935760498047}
{"validation_loss": 5.378016471862793, "time_this_iter_s": 0.049077749252319336, "done": false, "timesteps_total": null, "episodes_total": null, "training_iteration": 9, "trial_id": "aef0c_00102", "experiment_id": "cea9589f16564c87ba569f9e55b73541", "date": "2022-04-24_20-10-10", "timestamp": 1650823810, "time_total_s": 0.3860039710998535, "pid": 95824, "hostname": "marvin", "node_ip": "127.0.0.1", "config": {"layers": 1, "nodes": 25, "activation_function": "ReLU()", "optimizer_name": "lbfgs", "lr": 0.00031708213771730994, "number_of_minibatches": 1}, "time_since_restore": 0.3860039710998535, "timesteps_since_restore": 0, "iterations_since_restore": 9, "warmup_time": 0.0017859935760498047}
{"validation_loss": 4.774481296539307, "time_this_iter_s": 0.04090118408203125, "done": false, "timesteps_total": null, "episodes_total": null, "training_iteration": 10, "trial_id": "aef0c_00102", "experiment_id": "cea9589f16564c87ba569f9e55b73541", "date": "2022-04-24_20-10-10", "timestamp": 1650823810, "time_total_s": 0.42690515518188477, "pid": 95824, "hostname": "marvin", "node_ip": "127.0.0.1", "config": {"layers": 1, "nodes": 25, "activation_function": "ReLU()", "optimizer_name": "lbfgs", "lr": 0.00031708213771730994, "number_of_minibatches": 1}, "time_since_restore": 0.42690515518188477, "timesteps_since_restore": 0, "iterations_since_restore": 10, "warmup_time": 0.0017859935760498047}
{"validation_loss": 4.435053825378418, "time_this_iter_s": 0.04394173622131348, "done": false, "timesteps_total": null, "episodes_total": null, "training_iteration": 11, "trial_id": "aef0c_00102", "experiment_id": "cea9589f16564c87ba569f9e55b73541", "date": "2022-04-24_20-10-10", "timestamp": 1650823810, "time_total_s": 0.47084689140319824, "pid": 95824, "hostname": "marvin", "node_ip": "127.0.0.1", "config": {"layers": 1, "nodes": 25, "activation_function": "ReLU()", "optimizer_name": "lbfgs", "lr": 0.00031708213771730994, "number_of_minibatches": 1}, "time_since_restore": 0.47084689140319824, "timesteps_since_restore": 0, "iterations_since_restore": 11, "warmup_time": 0.0017859935760498047}
{"validation_loss": 4.168875694274902, "time_this_iter_s": 0.04477739334106445, "done": false, "timesteps_total": null, "episodes_total": null, "training_iteration": 12, "trial_id": "aef0c_00102", "experiment_id": "cea9589f16564c87ba569f9e55b73541", "date": "2022-04-24_20-10-10", "timestamp": 1650823810, "time_total_s": 0.5156242847442627, "pid": 95824, "hostname": "marvin", "node_ip": "127.0.0.1", "config": {"layers": 1, "nodes": 25, "activation_function": "ReLU()", "optimizer_name": "lbfgs", "lr": 0.00031708213771730994, "number_of_minibatches": 1}, "time_since_restore": 0.5156242847442627, "timesteps_since_restore": 0, "iterations_since_restore": 12, "warmup_time": 0.0017859935760498047}
{"validation_loss": 3.9503560066223145, "time_this_iter_s": 0.047299861907958984, "done": false, "timesteps_total": null, "episodes_total": null, "training_iteration": 13, "trial_id": "aef0c_00102", "experiment_id": "cea9589f16564c87ba569f9e55b73541", "date": "2022-04-24_20-10-10", "timestamp": 1650823810, "time_total_s": 0.5629241466522217, "pid": 95824, "hostname": "marvin", "node_ip": "127.0.0.1", "config": {"layers": 1, "nodes": 25, "activation_function": "ReLU()", "optimizer_name": "lbfgs", "lr": 0.00031708213771730994, "number_of_minibatches": 1}, "time_since_restore": 0.5629241466522217, "timesteps_since_restore": 0, "iterations_since_restore": 13, "warmup_time": 0.0017859935760498047}
{"validation_loss": 3.7403297424316406, "time_this_iter_s": 0.03672194480895996, "done": false, "timesteps_total": null, "episodes_total": null, "training_iteration": 14, "trial_id": "aef0c_00102", "experiment_id": "cea9589f16564c87ba569f9e55b73541", "date": "2022-04-24_20-10-10", "timestamp": 1650823810, "time_total_s": 0.5996460914611816, "pid": 95824, "hostname": "marvin", "node_ip": "127.0.0.1", "config": {"layers": 1, "nodes": 25, "activation_function": "ReLU()", "optimizer_name": "lbfgs", "lr": 0.00031708213771730994, "number_of_minibatches": 1}, "time_since_restore": 0.5996460914611816, "timesteps_since_restore": 0, "iterations_since_restore": 14, "warmup_time": 0.0017859935760498047}
{"validation_loss": 3.4967517852783203, "time_this_iter_s": 0.03508114814758301, "done": false, "timesteps_total": null, "episodes_total": null, "training_iteration": 15, "trial_id": "aef0c_00102", "experiment_id": "cea9589f16564c87ba569f9e55b73541", "date": "2022-04-24_20-10-10", "timestamp": 1650823810, "time_total_s": 0.6347272396087646, "pid": 95824, "hostname": "marvin", "node_ip": "127.0.0.1", "config": {"layers": 1, "nodes": 25, "activation_function": "ReLU()", "optimizer_name": "lbfgs", "lr": 0.00031708213771730994, "number_of_minibatches": 1}, "time_since_restore": 0.6347272396087646, "timesteps_since_restore": 0, "iterations_since_restore": 15, "warmup_time": 0.0017859935760498047}
{"validation_loss": 3.284170627593994, "time_this_iter_s": 0.035516977310180664, "done": false, "timesteps_total": null, "episodes_total": null, "training_iteration": 16, "trial_id": "aef0c_00102", "experiment_id": "cea9589f16564c87ba569f9e55b73541", "date": "2022-04-24_20-10-10", "timestamp": 1650823810, "time_total_s": 0.6702442169189453, "pid": 95824, "hostname": "marvin", "node_ip": "127.0.0.1", "config": {"layers": 1, "nodes": 25, "activation_function": "ReLU()", "optimizer_name": "lbfgs", "lr": 0.00031708213771730994, "number_of_minibatches": 1}, "time_since_restore": 0.6702442169189453, "timesteps_since_restore": 0, "iterations_since_restore": 16, "warmup_time": 0.0017859935760498047}
{"validation_loss": 3.128080368041992, "time_this_iter_s": 0.04064583778381348, "done": false, "timesteps_total": null, "episodes_total": null, "training_iteration": 17, "trial_id": "aef0c_00102", "experiment_id": "cea9589f16564c87ba569f9e55b73541", "date": "2022-04-24_20-10-10", "timestamp": 1650823810, "time_total_s": 0.7108900547027588, "pid": 95824, "hostname": "marvin", "node_ip": "127.0.0.1", "config": {"layers": 1, "nodes": 25, "activation_function": "ReLU()", "optimizer_name": "lbfgs", "lr": 0.00031708213771730994, "number_of_minibatches": 1}, "time_since_restore": 0.7108900547027588, "timesteps_since_restore": 0, "iterations_since_restore": 17, "warmup_time": 0.0017859935760498047}
{"validation_loss": 3.0021119117736816, "time_this_iter_s": 0.04481101036071777, "done": false, "timesteps_total": null, "episodes_total": null, "training_iteration": 18, "trial_id": "aef0c_00102", "experiment_id": "cea9589f16564c87ba569f9e55b73541", "date": "2022-04-24_20-10-10", "timestamp": 1650823810, "time_total_s": 0.7557010650634766, "pid": 95824, "hostname": "marvin", "node_ip": "127.0.0.1", "config": {"layers": 1, "nodes": 25, "activation_function": "ReLU()", "optimizer_name": "lbfgs", "lr": 0.00031708213771730994, "number_of_minibatches": 1}, "time_since_restore": 0.7557010650634766, "timesteps_since_restore": 0, "iterations_since_restore": 18, "warmup_time": 0.0017859935760498047}
{"validation_loss": 2.8804569244384766, "time_this_iter_s": 0.04850602149963379, "done": false, "timesteps_total": null, "episodes_total": null, "training_iteration": 19, "trial_id": "aef0c_00102", "experiment_id": "cea9589f16564c87ba569f9e55b73541", "date": "2022-04-24_20-10-10", "timestamp": 1650823810, "time_total_s": 0.8042070865631104, "pid": 95824, "hostname": "marvin", "node_ip": "127.0.0.1", "config": {"layers": 1, "nodes": 25, "activation_function": "ReLU()", "optimizer_name": "lbfgs", "lr": 0.00031708213771730994, "number_of_minibatches": 1}, "time_since_restore": 0.8042070865631104, "timesteps_since_restore": 0, "iterations_since_restore": 19, "warmup_time": 0.0017859935760498047}
{"validation_loss": 2.743215322494507, "time_this_iter_s": 0.043554067611694336, "done": true, "timesteps_total": null, "episodes_total": null, "training_iteration": 20, "trial_id": "aef0c_00102", "experiment_id": "cea9589f16564c87ba569f9e55b73541", "date": "2022-04-24_20-10-10", "timestamp": 1650823810, "time_total_s": 0.8477611541748047, "pid": 95824, "hostname": "marvin", "node_ip": "127.0.0.1", "config": {"layers": 1, "nodes": 25, "activation_function": "ReLU()", "optimizer_name": "lbfgs", "lr": 0.00031708213771730994, "number_of_minibatches": 1}, "time_since_restore": 0.8477611541748047, "timesteps_since_restore": 0, "iterations_since_restore": 20, "warmup_time": 0.0017859935760498047}
