{"validation_loss": 0.5200515389442444, "time_this_iter_s": 0.027765989303588867, "done": false, "timesteps_total": null, "episodes_total": null, "training_iteration": 1, "trial_id": "546e0_00177", "experiment_id": "2ed7c171d7dc486ba9954a40052144cb", "date": "2022-04-24_18-06-21", "timestamp": 1650816381, "time_total_s": 0.027765989303588867, "pid": 93573, "hostname": "marvin", "node_ip": "127.0.0.1", "config": {"layers": 1, "nodes": 18, "lr": 0.005797323378053885, "optimizer_name": "lbfgs", "number_of_minibatches": 1}, "time_since_restore": 0.027765989303588867, "timesteps_since_restore": 0, "iterations_since_restore": 1, "warmup_time": 0.0016789436340332031}
{"validation_loss": 0.39360925555229187, "time_this_iter_s": 0.05098700523376465, "done": true, "timesteps_total": null, "episodes_total": null, "training_iteration": 2, "trial_id": "546e0_00177", "experiment_id": "2ed7c171d7dc486ba9954a40052144cb", "date": "2022-04-24_18-06-22", "timestamp": 1650816382, "time_total_s": 0.07875299453735352, "pid": 93573, "hostname": "marvin", "node_ip": "127.0.0.1", "config": {"layers": 1, "nodes": 18, "lr": 0.005797323378053885, "optimizer_name": "lbfgs", "number_of_minibatches": 1}, "time_since_restore": 0.07875299453735352, "timesteps_since_restore": 0, "iterations_since_restore": 2, "warmup_time": 0.0016789436340332031}
