{"validation_loss": 0.3867809772491455, "time_this_iter_s": 0.016061067581176758, "done": false, "timesteps_total": null, "episodes_total": null, "training_iteration": 1, "trial_id": "546e0_00070", "experiment_id": "f5ed7671576f4e04b2c584e0493a3e7d", "date": "2022-04-24_18-05-42", "timestamp": 1650816342, "time_total_s": 0.016061067581176758, "pid": 93429, "hostname": "marvin", "node_ip": "127.0.0.1", "config": {"layers": 3, "nodes": 39, "lr": 0.00025897777233017374, "optimizer_name": "adam", "number_of_minibatches": 1}, "time_since_restore": 0.016061067581176758, "timesteps_since_restore": 0, "iterations_since_restore": 1, "warmup_time": 0.0051190853118896484}
{"validation_loss": 0.37651169300079346, "time_this_iter_s": 0.03331398963928223, "done": false, "timesteps_total": null, "episodes_total": null, "training_iteration": 2, "trial_id": "546e0_00070", "experiment_id": "f5ed7671576f4e04b2c584e0493a3e7d", "date": "2022-04-24_18-05-42", "timestamp": 1650816342, "time_total_s": 0.049375057220458984, "pid": 93429, "hostname": "marvin", "node_ip": "127.0.0.1", "config": {"layers": 3, "nodes": 39, "lr": 0.00025897777233017374, "optimizer_name": "adam", "number_of_minibatches": 1}, "time_since_restore": 0.049375057220458984, "timesteps_since_restore": 0, "iterations_since_restore": 2, "warmup_time": 0.0051190853118896484}
{"validation_loss": 0.3669719696044922, "time_this_iter_s": 0.02642512321472168, "done": false, "timesteps_total": null, "episodes_total": null, "training_iteration": 3, "trial_id": "546e0_00070", "experiment_id": "f5ed7671576f4e04b2c584e0493a3e7d", "date": "2022-04-24_18-05-42", "timestamp": 1650816342, "time_total_s": 0.07580018043518066, "pid": 93429, "hostname": "marvin", "node_ip": "127.0.0.1", "config": {"layers": 3, "nodes": 39, "lr": 0.00025897777233017374, "optimizer_name": "adam", "number_of_minibatches": 1}, "time_since_restore": 0.07580018043518066, "timesteps_since_restore": 0, "iterations_since_restore": 3, "warmup_time": 0.0051190853118896484}
{"validation_loss": 0.3581492602825165, "time_this_iter_s": 0.017184972763061523, "done": false, "timesteps_total": null, "episodes_total": null, "training_iteration": 4, "trial_id": "546e0_00070", "experiment_id": "f5ed7671576f4e04b2c584e0493a3e7d", "date": "2022-04-24_18-05-42", "timestamp": 1650816342, "time_total_s": 0.09298515319824219, "pid": 93429, "hostname": "marvin", "node_ip": "127.0.0.1", "config": {"layers": 3, "nodes": 39, "lr": 0.00025897777233017374, "optimizer_name": "adam", "number_of_minibatches": 1}, "time_since_restore": 0.09298515319824219, "timesteps_since_restore": 0, "iterations_since_restore": 4, "warmup_time": 0.0051190853118896484}
{"validation_loss": 0.3500318229198456, "time_this_iter_s": 0.019776105880737305, "done": true, "timesteps_total": null, "episodes_total": null, "training_iteration": 5, "trial_id": "546e0_00070", "experiment_id": "f5ed7671576f4e04b2c584e0493a3e7d", "date": "2022-04-24_18-05-42", "timestamp": 1650816342, "time_total_s": 0.11276125907897949, "pid": 93429, "hostname": "marvin", "node_ip": "127.0.0.1", "config": {"layers": 3, "nodes": 39, "lr": 0.00025897777233017374, "optimizer_name": "adam", "number_of_minibatches": 1}, "time_since_restore": 0.11276125907897949, "timesteps_since_restore": 0, "iterations_since_restore": 5, "warmup_time": 0.0051190853118896484}
