{"validation_loss": 0.2709173262119293, "time_this_iter_s": 0.0038788318634033203, "done": false, "timesteps_total": null, "episodes_total": null, "training_iteration": 1, "trial_id": "546e0_00198", "experiment_id": "415cbbeecc114832bb56838492c455e2", "date": "2022-04-24_18-06-29", "timestamp": 1650816389, "time_total_s": 0.0038788318634033203, "pid": 93603, "hostname": "marvin", "node_ip": "127.0.0.1", "config": {"layers": 1, "nodes": 8, "lr": 0.01649073741045851, "optimizer_name": "adam", "number_of_minibatches": 1}, "time_since_restore": 0.0038788318634033203, "timesteps_since_restore": 0, "iterations_since_restore": 1, "warmup_time": 0.002488851547241211}
{"validation_loss": 0.27324792742729187, "time_this_iter_s": 0.0049479007720947266, "done": false, "timesteps_total": null, "episodes_total": null, "training_iteration": 2, "trial_id": "546e0_00198", "experiment_id": "415cbbeecc114832bb56838492c455e2", "date": "2022-04-24_18-06-29", "timestamp": 1650816389, "time_total_s": 0.008826732635498047, "pid": 93603, "hostname": "marvin", "node_ip": "127.0.0.1", "config": {"layers": 1, "nodes": 8, "lr": 0.01649073741045851, "optimizer_name": "adam", "number_of_minibatches": 1}, "time_since_restore": 0.008826732635498047, "timesteps_since_restore": 0, "iterations_since_restore": 2, "warmup_time": 0.002488851547241211}
{"validation_loss": 0.2694362699985504, "time_this_iter_s": 0.003704071044921875, "done": false, "timesteps_total": null, "episodes_total": null, "training_iteration": 3, "trial_id": "546e0_00198", "experiment_id": "415cbbeecc114832bb56838492c455e2", "date": "2022-04-24_18-06-29", "timestamp": 1650816389, "time_total_s": 0.012530803680419922, "pid": 93603, "hostname": "marvin", "node_ip": "127.0.0.1", "config": {"layers": 1, "nodes": 8, "lr": 0.01649073741045851, "optimizer_name": "adam", "number_of_minibatches": 1}, "time_since_restore": 0.012530803680419922, "timesteps_since_restore": 0, "iterations_since_restore": 3, "warmup_time": 0.002488851547241211}
{"validation_loss": 0.2628576457500458, "time_this_iter_s": 0.0039103031158447266, "done": false, "timesteps_total": null, "episodes_total": null, "training_iteration": 4, "trial_id": "546e0_00198", "experiment_id": "415cbbeecc114832bb56838492c455e2", "date": "2022-04-24_18-06-29", "timestamp": 1650816389, "time_total_s": 0.01644110679626465, "pid": 93603, "hostname": "marvin", "node_ip": "127.0.0.1", "config": {"layers": 1, "nodes": 8, "lr": 0.01649073741045851, "optimizer_name": "adam", "number_of_minibatches": 1}, "time_since_restore": 0.01644110679626465, "timesteps_since_restore": 0, "iterations_since_restore": 4, "warmup_time": 0.002488851547241211}
{"validation_loss": 0.2591424286365509, "time_this_iter_s": 0.005714893341064453, "done": false, "timesteps_total": null, "episodes_total": null, "training_iteration": 5, "trial_id": "546e0_00198", "experiment_id": "415cbbeecc114832bb56838492c455e2", "date": "2022-04-24_18-06-29", "timestamp": 1650816389, "time_total_s": 0.0221560001373291, "pid": 93603, "hostname": "marvin", "node_ip": "127.0.0.1", "config": {"layers": 1, "nodes": 8, "lr": 0.01649073741045851, "optimizer_name": "adam", "number_of_minibatches": 1}, "time_since_restore": 0.0221560001373291, "timesteps_since_restore": 0, "iterations_since_restore": 5, "warmup_time": 0.002488851547241211}
{"validation_loss": 0.25835075974464417, "time_this_iter_s": 0.004261970520019531, "done": false, "timesteps_total": null, "episodes_total": null, "training_iteration": 6, "trial_id": "546e0_00198", "experiment_id": "415cbbeecc114832bb56838492c455e2", "date": "2022-04-24_18-06-29", "timestamp": 1650816389, "time_total_s": 0.026417970657348633, "pid": 93603, "hostname": "marvin", "node_ip": "127.0.0.1", "config": {"layers": 1, "nodes": 8, "lr": 0.01649073741045851, "optimizer_name": "adam", "number_of_minibatches": 1}, "time_since_restore": 0.026417970657348633, "timesteps_since_restore": 0, "iterations_since_restore": 6, "warmup_time": 0.002488851547241211}
{"validation_loss": 0.2568261921405792, "time_this_iter_s": 0.0045931339263916016, "done": false, "timesteps_total": null, "episodes_total": null, "training_iteration": 7, "trial_id": "546e0_00198", "experiment_id": "415cbbeecc114832bb56838492c455e2", "date": "2022-04-24_18-06-29", "timestamp": 1650816389, "time_total_s": 0.031011104583740234, "pid": 93603, "hostname": "marvin", "node_ip": "127.0.0.1", "config": {"layers": 1, "nodes": 8, "lr": 0.01649073741045851, "optimizer_name": "adam", "number_of_minibatches": 1}, "time_since_restore": 0.031011104583740234, "timesteps_since_restore": 0, "iterations_since_restore": 7, "warmup_time": 0.002488851547241211}
{"validation_loss": 0.25296109914779663, "time_this_iter_s": 0.004045724868774414, "done": false, "timesteps_total": null, "episodes_total": null, "training_iteration": 8, "trial_id": "546e0_00198", "experiment_id": "415cbbeecc114832bb56838492c455e2", "date": "2022-04-24_18-06-29", "timestamp": 1650816389, "time_total_s": 0.03505682945251465, "pid": 93603, "hostname": "marvin", "node_ip": "127.0.0.1", "config": {"layers": 1, "nodes": 8, "lr": 0.01649073741045851, "optimizer_name": "adam", "number_of_minibatches": 1}, "time_since_restore": 0.03505682945251465, "timesteps_since_restore": 0, "iterations_since_restore": 8, "warmup_time": 0.002488851547241211}
{"validation_loss": 0.24826952815055847, "time_this_iter_s": 0.011059999465942383, "done": false, "timesteps_total": null, "episodes_total": null, "training_iteration": 9, "trial_id": "546e0_00198", "experiment_id": "415cbbeecc114832bb56838492c455e2", "date": "2022-04-24_18-06-29", "timestamp": 1650816389, "time_total_s": 0.04611682891845703, "pid": 93603, "hostname": "marvin", "node_ip": "127.0.0.1", "config": {"layers": 1, "nodes": 8, "lr": 0.01649073741045851, "optimizer_name": "adam", "number_of_minibatches": 1}, "time_since_restore": 0.04611682891845703, "timesteps_since_restore": 0, "iterations_since_restore": 9, "warmup_time": 0.002488851547241211}
{"validation_loss": 0.24470144510269165, "time_this_iter_s": 0.003434896469116211, "done": false, "timesteps_total": null, "episodes_total": null, "training_iteration": 10, "trial_id": "546e0_00198", "experiment_id": "415cbbeecc114832bb56838492c455e2", "date": "2022-04-24_18-06-29", "timestamp": 1650816389, "time_total_s": 0.04955172538757324, "pid": 93603, "hostname": "marvin", "node_ip": "127.0.0.1", "config": {"layers": 1, "nodes": 8, "lr": 0.01649073741045851, "optimizer_name": "adam", "number_of_minibatches": 1}, "time_since_restore": 0.04955172538757324, "timesteps_since_restore": 0, "iterations_since_restore": 10, "warmup_time": 0.002488851547241211}
{"validation_loss": 0.24252527952194214, "time_this_iter_s": 0.003814220428466797, "done": false, "timesteps_total": null, "episodes_total": null, "training_iteration": 11, "trial_id": "546e0_00198", "experiment_id": "415cbbeecc114832bb56838492c455e2", "date": "2022-04-24_18-06-29", "timestamp": 1650816389, "time_total_s": 0.05336594581604004, "pid": 93603, "hostname": "marvin", "node_ip": "127.0.0.1", "config": {"layers": 1, "nodes": 8, "lr": 0.01649073741045851, "optimizer_name": "adam", "number_of_minibatches": 1}, "time_since_restore": 0.05336594581604004, "timesteps_since_restore": 0, "iterations_since_restore": 11, "warmup_time": 0.002488851547241211}
{"validation_loss": 0.24027490615844727, "time_this_iter_s": 0.0035080909729003906, "done": false, "timesteps_total": null, "episodes_total": null, "training_iteration": 12, "trial_id": "546e0_00198", "experiment_id": "415cbbeecc114832bb56838492c455e2", "date": "2022-04-24_18-06-29", "timestamp": 1650816389, "time_total_s": 0.05687403678894043, "pid": 93603, "hostname": "marvin", "node_ip": "127.0.0.1", "config": {"layers": 1, "nodes": 8, "lr": 0.01649073741045851, "optimizer_name": "adam", "number_of_minibatches": 1}, "time_since_restore": 0.05687403678894043, "timesteps_since_restore": 0, "iterations_since_restore": 12, "warmup_time": 0.002488851547241211}
{"validation_loss": 0.23668795824050903, "time_this_iter_s": 0.004211902618408203, "done": false, "timesteps_total": null, "episodes_total": null, "training_iteration": 13, "trial_id": "546e0_00198", "experiment_id": "415cbbeecc114832bb56838492c455e2", "date": "2022-04-24_18-06-29", "timestamp": 1650816389, "time_total_s": 0.06108593940734863, "pid": 93603, "hostname": "marvin", "node_ip": "127.0.0.1", "config": {"layers": 1, "nodes": 8, "lr": 0.01649073741045851, "optimizer_name": "adam", "number_of_minibatches": 1}, "time_since_restore": 0.06108593940734863, "timesteps_since_restore": 0, "iterations_since_restore": 13, "warmup_time": 0.002488851547241211}
{"validation_loss": 0.23199687898159027, "time_this_iter_s": 0.003201007843017578, "done": false, "timesteps_total": null, "episodes_total": null, "training_iteration": 14, "trial_id": "546e0_00198", "experiment_id": "415cbbeecc114832bb56838492c455e2", "date": "2022-04-24_18-06-29", "timestamp": 1650816389, "time_total_s": 0.06428694725036621, "pid": 93603, "hostname": "marvin", "node_ip": "127.0.0.1", "config": {"layers": 1, "nodes": 8, "lr": 0.01649073741045851, "optimizer_name": "adam", "number_of_minibatches": 1}, "time_since_restore": 0.06428694725036621, "timesteps_since_restore": 0, "iterations_since_restore": 14, "warmup_time": 0.002488851547241211}
{"validation_loss": 0.2272540032863617, "time_this_iter_s": 0.003139972686767578, "done": false, "timesteps_total": null, "episodes_total": null, "training_iteration": 15, "trial_id": "546e0_00198", "experiment_id": "415cbbeecc114832bb56838492c455e2", "date": "2022-04-24_18-06-29", "timestamp": 1650816389, "time_total_s": 0.06742691993713379, "pid": 93603, "hostname": "marvin", "node_ip": "127.0.0.1", "config": {"layers": 1, "nodes": 8, "lr": 0.01649073741045851, "optimizer_name": "adam", "number_of_minibatches": 1}, "time_since_restore": 0.06742691993713379, "timesteps_since_restore": 0, "iterations_since_restore": 15, "warmup_time": 0.002488851547241211}
{"validation_loss": 0.22305044531822205, "time_this_iter_s": 0.002997159957885742, "done": false, "timesteps_total": null, "episodes_total": null, "training_iteration": 16, "trial_id": "546e0_00198", "experiment_id": "415cbbeecc114832bb56838492c455e2", "date": "2022-04-24_18-06-29", "timestamp": 1650816389, "time_total_s": 0.07042407989501953, "pid": 93603, "hostname": "marvin", "node_ip": "127.0.0.1", "config": {"layers": 1, "nodes": 8, "lr": 0.01649073741045851, "optimizer_name": "adam", "number_of_minibatches": 1}, "time_since_restore": 0.07042407989501953, "timesteps_since_restore": 0, "iterations_since_restore": 16, "warmup_time": 0.002488851547241211}
{"validation_loss": 0.2189813256263733, "time_this_iter_s": 0.002975940704345703, "done": false, "timesteps_total": null, "episodes_total": null, "training_iteration": 17, "trial_id": "546e0_00198", "experiment_id": "415cbbeecc114832bb56838492c455e2", "date": "2022-04-24_18-06-29", "timestamp": 1650816389, "time_total_s": 0.07340002059936523, "pid": 93603, "hostname": "marvin", "node_ip": "127.0.0.1", "config": {"layers": 1, "nodes": 8, "lr": 0.01649073741045851, "optimizer_name": "adam", "number_of_minibatches": 1}, "time_since_restore": 0.07340002059936523, "timesteps_since_restore": 0, "iterations_since_restore": 17, "warmup_time": 0.002488851547241211}
{"validation_loss": 0.2143358290195465, "time_this_iter_s": 0.003134012222290039, "done": false, "timesteps_total": null, "episodes_total": null, "training_iteration": 18, "trial_id": "546e0_00198", "experiment_id": "415cbbeecc114832bb56838492c455e2", "date": "2022-04-24_18-06-29", "timestamp": 1650816389, "time_total_s": 0.07653403282165527, "pid": 93603, "hostname": "marvin", "node_ip": "127.0.0.1", "config": {"layers": 1, "nodes": 8, "lr": 0.01649073741045851, "optimizer_name": "adam", "number_of_minibatches": 1}, "time_since_restore": 0.07653403282165527, "timesteps_since_restore": 0, "iterations_since_restore": 18, "warmup_time": 0.002488851547241211}
{"validation_loss": 0.209070086479187, "time_this_iter_s": 0.003451824188232422, "done": false, "timesteps_total": null, "episodes_total": null, "training_iteration": 19, "trial_id": "546e0_00198", "experiment_id": "415cbbeecc114832bb56838492c455e2", "date": "2022-04-24_18-06-29", "timestamp": 1650816389, "time_total_s": 0.0799858570098877, "pid": 93603, "hostname": "marvin", "node_ip": "127.0.0.1", "config": {"layers": 1, "nodes": 8, "lr": 0.01649073741045851, "optimizer_name": "adam", "number_of_minibatches": 1}, "time_since_restore": 0.0799858570098877, "timesteps_since_restore": 0, "iterations_since_restore": 19, "warmup_time": 0.002488851547241211}
{"validation_loss": 0.20379416644573212, "time_this_iter_s": 0.004197120666503906, "done": true, "timesteps_total": null, "episodes_total": null, "training_iteration": 20, "trial_id": "546e0_00198", "experiment_id": "415cbbeecc114832bb56838492c455e2", "date": "2022-04-24_18-06-29", "timestamp": 1650816389, "time_total_s": 0.0841829776763916, "pid": 93603, "hostname": "marvin", "node_ip": "127.0.0.1", "config": {"layers": 1, "nodes": 8, "lr": 0.01649073741045851, "optimizer_name": "adam", "number_of_minibatches": 1}, "time_since_restore": 0.0841829776763916, "timesteps_since_restore": 0, "iterations_since_restore": 20, "warmup_time": 0.002488851547241211}
