{"validation_loss": 0.6807130575180054, "time_this_iter_s": 0.05503225326538086, "done": false, "timesteps_total": null, "episodes_total": null, "training_iteration": 1, "trial_id": "546e0_00162", "experiment_id": "c3a3e6eb65db467ea2587cdcf05c56c6", "date": "2022-04-24_18-06-17", "timestamp": 1650816377, "time_total_s": 0.05503225326538086, "pid": 93555, "hostname": "marvin", "node_ip": "127.0.0.1", "config": {"layers": 1, "nodes": 37, "lr": 0.0023995389883879766, "optimizer_name": "lbfgs", "number_of_minibatches": 1}, "time_since_restore": 0.05503225326538086, "timesteps_since_restore": 0, "iterations_since_restore": 1, "warmup_time": 0.005491971969604492}
{"validation_loss": 0.5675442814826965, "time_this_iter_s": 0.05716896057128906, "done": false, "timesteps_total": null, "episodes_total": null, "training_iteration": 2, "trial_id": "546e0_00162", "experiment_id": "c3a3e6eb65db467ea2587cdcf05c56c6", "date": "2022-04-24_18-06-17", "timestamp": 1650816377, "time_total_s": 0.11220121383666992, "pid": 93555, "hostname": "marvin", "node_ip": "127.0.0.1", "config": {"layers": 1, "nodes": 37, "lr": 0.0023995389883879766, "optimizer_name": "lbfgs", "number_of_minibatches": 1}, "time_since_restore": 0.11220121383666992, "timesteps_since_restore": 0, "iterations_since_restore": 2, "warmup_time": 0.005491971969604492}
{"validation_loss": 0.46944957971572876, "time_this_iter_s": 0.04799604415893555, "done": false, "timesteps_total": null, "episodes_total": null, "training_iteration": 3, "trial_id": "546e0_00162", "experiment_id": "c3a3e6eb65db467ea2587cdcf05c56c6", "date": "2022-04-24_18-06-17", "timestamp": 1650816377, "time_total_s": 0.16019725799560547, "pid": 93555, "hostname": "marvin", "node_ip": "127.0.0.1", "config": {"layers": 1, "nodes": 37, "lr": 0.0023995389883879766, "optimizer_name": "lbfgs", "number_of_minibatches": 1}, "time_since_restore": 0.16019725799560547, "timesteps_since_restore": 0, "iterations_since_restore": 3, "warmup_time": 0.005491971969604492}
{"validation_loss": 0.40979453921318054, "time_this_iter_s": 0.04888796806335449, "done": false, "timesteps_total": null, "episodes_total": null, "training_iteration": 4, "trial_id": "546e0_00162", "experiment_id": "c3a3e6eb65db467ea2587cdcf05c56c6", "date": "2022-04-24_18-06-18", "timestamp": 1650816378, "time_total_s": 0.20908522605895996, "pid": 93555, "hostname": "marvin", "node_ip": "127.0.0.1", "config": {"layers": 1, "nodes": 37, "lr": 0.0023995389883879766, "optimizer_name": "lbfgs", "number_of_minibatches": 1}, "time_since_restore": 0.20908522605895996, "timesteps_since_restore": 0, "iterations_since_restore": 4, "warmup_time": 0.005491971969604492}
{"validation_loss": 0.3680562674999237, "time_this_iter_s": 0.05197596549987793, "done": true, "timesteps_total": null, "episodes_total": null, "training_iteration": 5, "trial_id": "546e0_00162", "experiment_id": "c3a3e6eb65db467ea2587cdcf05c56c6", "date": "2022-04-24_18-06-18", "timestamp": 1650816378, "time_total_s": 0.2610611915588379, "pid": 93555, "hostname": "marvin", "node_ip": "127.0.0.1", "config": {"layers": 1, "nodes": 37, "lr": 0.0023995389883879766, "optimizer_name": "lbfgs", "number_of_minibatches": 1}, "time_since_restore": 0.2610611915588379, "timesteps_since_restore": 0, "iterations_since_restore": 5, "warmup_time": 0.005491971969604492}
